experiment3/adders.v
module half_adder(input a, input b, output sum, output carry);
    assign sum   = a ^ b;   
    assign carry = a & b;   
endmodule

module full_adder(input a, input b, input cin, output sum, output carry);
    wire s1, c1, c2;

    half_adder ha1(.a(a), .b(b), .sum(s1), .carry(c1));
    half_adder ha2(.a(s1), .b(cin), .sum(sum), .carry(c2));

    assign carry = c1 | c2;
endmodule

experiment3/adders_tb.v
`timescale 1ns/1ps
module adders_tb;
    reg a, b, cin;
    wire sum_half, carry_half;
    wire sum_full, carry_full;

    half_adder HA(.a(a), .b(b), .sum(sum_half), .carry(carry_half));

    full_adder FA(.a(a), .b(b), .cin(cin), .sum(sum_full), .carry(carry_full));

    // Waveform dump
    initial begin
        $dumpfile("adders.vcd");
        $dumpvars(0, adders_tb);
    end

    initial begin
        $display("A B Cin | HA_Sum HA_Carry | FA_Sum FA_Carry");

        a=0; b=0; cin=0; #10;
        a=0; b=0; cin=1; #10;
        a=0; b=1; cin=0; #10;
        a=0; b=1; cin=1; #10;
        a=1; b=0; cin=0; #10;
        a=1; b=0; cin=1; #10;
        a=1; b=1; cin=0; #10;
        a=1; b=1; cin=1; #10;

        $finish;
    end
    initial begin
        $monitor("%b %b  %b  |    %b       %b     |    %b       %b", 
                  a, b, cin, sum_half, carry_half, sum_full, carry_full);
    end
endmodule

experiment3/adders.vcd
$date
	Mon Sep 01 23:16:11 2025
$end
$version
	Icarus Verilog
$end
$timescale
	1ps
$end
$scope module adders_tb $end
$var wire 1 ! sum_half $end
$var wire 1 " sum_full $end
$var wire 1 # carry_half $end
$var wire 1 $ carry_full $end
$var reg 1 % a $end
$var reg 1 & b $end
$var reg 1 ' cin $end
$scope module FA $end
$var wire 1 % a $end
$var wire 1 & b $end
$var wire 1 $ carry $end
$var wire 1 ' cin $end
$var wire 1 " sum $end
$var wire 1 ( s1 $end
$var wire 1 ) c2 $end
$var wire 1 * c1 $end
$scope module ha1 $end
$var wire 1 % a $end
$var wire 1 & b $end
$var wire 1 * carry $end
$var wire 1 ( sum $end
$upscope $end
$scope module ha2 $end
$var wire 1 ( a $end
$var wire 1 ' b $end
$var wire 1 ) carry $end
$var wire 1 " sum $end
$upscope $end
$upscope $end
$scope module HA $end
$var wire 1 % a $end
$var wire 1 & b $end
$var wire 1 # carry $end
$var wire 1 ! sum $end
$upscope $end
$upscope $end
$enddefinitions $end
$comment Show the parameter values. $end
$dumpall
$end
#0
$dumpvars
0*
0)
0(
0'
0&
0%
0$
0#
0"
0!
$end
#10000
1"
1'
#20000
1(
1!
0'
1&
#30000
1$
0"
1)
1'
#40000
0$
1"
0)
0'
0&
1%
#50000
1$
0"
1)
1'
#60000
0)
0(
1*
0!
1#
0'
1&
#70000
1"
1'
